policyglass/__init__.py
policyglass/action.py
policyglass/condition.py
policyglass/deprecated.py
policyglass/effective_arp.py
policyglass/models.py
policyglass/policy.py
policyglass/policy_shard.py
policyglass/principal.py
policyglass/protocols.py
policyglass/py.typed
policyglass/resource.py
policyglass/statement.py
policyglass/utils.py
policyglass-0.8.0.dist-info/LICENSE
policyglass-0.8.0.dist-info/METADATA
policyglass-0.8.0.dist-info/WHEEL
policyglass-0.8.0.dist-info/top_level.txt
policyglass-0.8.0.dist-info/RECORD
