Metadata-Version: 2.1
Name: policyglass
Version: 0.8.0
Summary: Understand the effective permissions of your policies
Home-page: https://github.com/CloudWanderer-io/PolicyGlass
Author: Sam Martin
Author-email: samjackmartin+policyglass@gmail.com
License: UNKNOWN
Platform: UNKNOWN
Requires-Python: >=3.6.0
License-File: LICENSE
Requires-Dist: pydantic
Requires-Dist: typing-extensions ; python_version < "3.8.0"
